README.txt
setup.cfg
setup.py
collective/__init__.py
collective.mediaAlbum.egg-info/PKG-INFO
collective.mediaAlbum.egg-info/SOURCES.txt
collective.mediaAlbum.egg-info/dependency_links.txt
collective.mediaAlbum.egg-info/entry_points.txt
collective.mediaAlbum.egg-info/namespace_packages.txt
collective.mediaAlbum.egg-info/not-zip-safe
collective.mediaAlbum.egg-info/paster_plugins.txt
collective.mediaAlbum.egg-info/requires.txt
collective.mediaAlbum.egg-info/top_level.txt
collective/mediaAlbum/__init__.py
collective/mediaAlbum/configure.zcml
collective/mediaAlbum/interfaces.py
collective/mediaAlbum/tests.py
collective/mediaAlbum/browser/__init__.py
collective/mediaAlbum/browser/albumView.pt
collective/mediaAlbum/browser/albumview.py
collective/mediaAlbum/browser/configure.zcml
collective/mediaAlbum/profiles/default/browserlayer.xml
collective/mediaAlbum/profiles/default/metadata.xml
docs/HISTORY.txt
docs/INSTALL.txt
docs/LICENSE.GPL
docs/LICENSE.txt