Metadata-Version: 1.0
Name: collective.mediaAlbum
Version: 0.3
Summary: Turn folders into albums that show your media in a user friendly interface (basically overrides Plone thumbnail view)
Home-page: http://svn.plone.org/svn/collective/
Author: David Jonas
Author-email: davidjonasdesign@gmail.com
License: GPL
Keywords: album plone images image link youtube vimeo mediashow quickupload folder
Platform: UNKNOWN
Classifier: Framework :: Plone
Classifier: Programming Language :: Python
